autosubtakeover/__init__.py
autosubtakeover/__main__.py
autosubtakeover/_version.py
autosubtakeover/command.py
autosubtakeover/error.py
autosubtakeover/path.py
autosubtakeover-0.1.dist-info/AUTHORS.rst
autosubtakeover-0.1.dist-info/LICENSE.txt
autosubtakeover-0.1.dist-info/METADATA
autosubtakeover-0.1.dist-info/WHEEL
autosubtakeover-0.1.dist-info/entry_points.txt
autosubtakeover-0.1.dist-info/top_level.txt
autosubtakeover-0.1.dist-info/RECORD
