Metadata-Version: 2.1
Name: autosubtakeover
Version: 0.1
Summary: autoSubTakeover
Home-page: https://github.com/jordyzomer/autosubtakeover
Author: Jordy Zomer
Author-email: jordy@simplyhacker.com
License: MIT
Download-URL: https://github.com/jordyzomer/autosubtakeover/archive/v_01.tar.gz
Platform: UNKNOWN
Classifier: License :: OSI Approved :: MIT License
Classifier: Programming Language :: Python :: 3
Classifier: Programming Language :: Python :: 3.7
Requires-Dist: click
Requires-Dist: asyncio
Requires-Dist: tornado
Requires-Dist: aiodns
Requires-Dist: pycares
Requires-Dist: tldextract
